simbench/__init__.py
simbench/converter/__init__.py
simbench/converter/auxiliary.py
simbench/converter/csv_data_manipulation.py
simbench/converter/csv_pp_converter.py
simbench/converter/format_information.py
simbench/converter/pp_net_manipulation.py
simbench/converter/read_and_write.py
simbench/converter/voltLvl.py
simbench/networks/__init__.py
simbench/networks/extract_simbench_grids_from_csv.py
simbench/networks/loadcases.py
simbench/networks/profiles.py
simbench/networks/simbench_code.py
simbench/networks/1-complete_data-mixed-all-0-sw/Coordinates.csv
simbench/networks/1-complete_data-mixed-all-0-sw/ExternalNet.csv
simbench/networks/1-complete_data-mixed-all-0-sw/Line.csv
simbench/networks/1-complete_data-mixed-all-0-sw/LineType.csv
simbench/networks/1-complete_data-mixed-all-0-sw/Load.csv
simbench/networks/1-complete_data-mixed-all-0-sw/LoadProfile.csv
simbench/networks/1-complete_data-mixed-all-0-sw/Measurement.csv
simbench/networks/1-complete_data-mixed-all-0-sw/Node.csv
simbench/networks/1-complete_data-mixed-all-0-sw/PowerPlant.csv
simbench/networks/1-complete_data-mixed-all-0-sw/PowerPlantProfile.csv
simbench/networks/1-complete_data-mixed-all-0-sw/RES.csv
simbench/networks/1-complete_data-mixed-all-0-sw/RESProfile.csv
simbench/networks/1-complete_data-mixed-all-0-sw/StudyCases.csv
simbench/networks/1-complete_data-mixed-all-0-sw/Substation.csv
simbench/networks/1-complete_data-mixed-all-0-sw/Switch.csv
simbench/networks/1-complete_data-mixed-all-0-sw/Transformer.csv
simbench/networks/1-complete_data-mixed-all-0-sw/TransformerType.csv
simbench/networks/1-complete_data-mixed-all-1-sw/Coordinates.csv
simbench/networks/1-complete_data-mixed-all-1-sw/DCLineType.csv
simbench/networks/1-complete_data-mixed-all-1-sw/ExternalNet.csv
simbench/networks/1-complete_data-mixed-all-1-sw/Line.csv
simbench/networks/1-complete_data-mixed-all-1-sw/LineType.csv
simbench/networks/1-complete_data-mixed-all-1-sw/Load.csv
simbench-1.6.1.dist-info/licenses/AUTHORS
simbench-1.6.1.dist-info/licenses/LICENSE
simbench-1.6.1.dist-info/METADATA
simbench-1.6.1.dist-info/WHEEL
simbench-1.6.1.dist-info/top_level.txt
simbench-1.6.1.dist-info/RECORD
