Metadata-Version: 2.4
Name: simbench
Version: 1.6.1
Summary: Electrical Power System Benchmark Models.
Author-email: Steffen Meinecke <steffen.meinecke@uni-kassel.de>
Maintainer-email: simbench Developers <simbench@uni-kassel.de>
License: Copyright (c) 2019-2021 by University of Kassel, TU Dortmund, RWTH Aachen University and Fraunhofer Institute for Energy Economics and Energy System Technology (IEE) Kassel and individual contributors (see AUTHORS file for details).
Project-URL: Homepage, https://www.simbench.net
Project-URL: Documentation, https://simbench.readthedocs.io
Project-URL: Source, https://www.github.com/e2nIEE/simbench
Project-URL: Repository, https://www.github.com/e2nIEE/simbench.git
Project-URL: Issues, https://www.github.com/e2nIEE/simbench/issues
Project-URL: Download, https://pypi.org/project/simbench/#files
Project-URL: Changelog, https://github.com/e2nIEE/simbench/blob/develop/CHANGELOG.rst
Keywords: benchmark grid,power system,network,grid planning,grid operation,grid generation methodology,comparability,reproducibility,electricity,energy,engineering,simulation,simbench,time series,future scenarios
Classifier: Development Status :: 5 - Production/Stable
Classifier: Environment :: Console
Classifier: Intended Audience :: Developers
Classifier: Intended Audience :: Education
Classifier: Intended Audience :: Science/Research
Classifier: License :: OSI Approved :: BSD License
Classifier: Natural Language :: English
Classifier: Operating System :: OS Independent
Classifier: Programming Language :: Python
Classifier: Programming Language :: Python :: 3
Classifier: Programming Language :: Python :: 3.9
Classifier: Programming Language :: Python :: 3.10
Classifier: Programming Language :: Python :: 3.11
Classifier: Programming Language :: Python :: 3.12
Requires-Python: >=3.9
License-File: LICENSE
License-File: AUTHORS
Requires-Dist: pandapower>=3.0.0
Provides-Extra: docs
Requires-Dist: numpydoc; extra == "docs"
Requires-Dist: sphinx; extra == "docs"
Requires-Dist: sphinx_rtd_theme; extra == "docs"
Requires-Dist: sphinx-pyproject; extra == "docs"
Provides-Extra: plotting
Requires-Dist: plotly>=3.1.1; extra == "plotting"
Requires-Dist: matplotlib; extra == "plotting"
Requires-Dist: igraph; extra == "plotting"
Requires-Dist: geopandas; extra == "plotting"
Requires-Dist: geojson; extra == "plotting"
Provides-Extra: test
Requires-Dist: pytest~=8.1; extra == "test"
Requires-Dist: pytest-xdist; extra == "test"
Requires-Dist: nbmake; extra == "test"
Provides-Extra: performance
Requires-Dist: ortools; extra == "performance"
Requires-Dist: numba>=0.25; extra == "performance"
Requires-Dist: lightsim2grid>=0.8.1; extra == "performance"
Provides-Extra: fileio
Requires-Dist: geopandas; extra == "fileio"
Provides-Extra: tutorials
Requires-Dist: matplotlib; extra == "tutorials"
Provides-Extra: all
Requires-Dist: plotly>=3.1.1; extra == "all"
Requires-Dist: matplotlib; extra == "all"
Requires-Dist: igraph; extra == "all"
Requires-Dist: geopandas; extra == "all"
Requires-Dist: geojson; extra == "all"
Requires-Dist: pytest~=8.1; extra == "all"
Requires-Dist: pytest-xdist; extra == "all"
Requires-Dist: nbmake; extra == "all"
Requires-Dist: ortools; extra == "all"
Requires-Dist: numba>=0.25; extra == "all"
Requires-Dist: lightsim2grid>=0.8.1; extra == "all"
Requires-Dist: geopandas; extra == "all"
Requires-Dist: matplotlib; extra == "all"
Dynamic: license-file
